LICENSE.txt
README.md
setup.cfg
setup.py
mc_sim_fin/__init__.py
mc_sim_fin/mc.py
mc_sim_fin.egg-info/PKG-INFO
mc_sim_fin.egg-info/SOURCES.txt
mc_sim_fin.egg-info/dependency_links.txt
mc_sim_fin.egg-info/requires.txt
mc_sim_fin.egg-info/top_level.txt
mc_sim_fin/utils/__init__.py
mc_sim_fin/utils/helpers.py