Metadata-Version: 2.1
Name: mc-sim-fin
Version: 1.0.0
Summary: montecarlo simulations/analysis library for finance
Home-page: https://github.com/gaugau3000/montecarlo_simulation_finance
Author: Gautier Pialat
Author-email: g.pialat@gmail.com
License: UNKNOWN
Keywords: finance montecarlo simulations backtest risk management
Platform: UNKNOWN
Classifier: Development Status :: 4 - Beta
Classifier: Intended Audience :: Financial and Insurance Industry
Classifier: Topic :: Office/Business :: Financial
Classifier: License :: OSI Approved :: MIT License
Classifier: Programming Language :: Python :: 3.7
Requires-Python: >=3.9, <4
License-File: LICENSE.txt
